instantcoffee/__init__.py
instantcoffee/cloudcredentials/__init__.py
instantcoffee/cloudcredentials/aws_validation.py
instantcoffee/cloudcredentials/validation.py
instantcoffee/connect.py
instantcoffee/kaffeeservice/__init__.py
instantcoffee/kaffeeservice/api.py
instantcoffee/kaffeeservice/consts.py
instantcoffee/kaffeeservice/exceptions.py
instant_coffee-0.1.1.dist-info/LICENSE
instant_coffee-0.1.1.dist-info/WHEEL
instant_coffee-0.1.1.dist-info/METADATA
instant_coffee-0.1.1.dist-info/RECORD
